{
  "collapse-filter": false,
  "search": "",
  "showTags": false,
  "showAttachments": true,
  "hideUnresolved": false,
  "showOrphans": true,
  "collapse-color-groups": false,
  "colorGroups": [],
  "collapse-display": false,
  "showArrow": true,
  "textFadeMultiplier": -1.5,
  "nodeSizeMultiplier": 0.840104166666667,
  "lineSizeMultiplier": 1.14635416666667,
  "collapse-forces": false,
  "centerStrength": 0.302083333333333,
  "repelStrength": 10,
  "linkStrength": 1,
  "linkDistance": 250,
  "scale": 1.0929739046750444,
  "close": true
}